fitnoise
