Metadata-Version: 1.0
Name: fitnoise
Version: 2.2
Summary: Statistical analysis of RNA-Seq, PAT-Seq, and microarray data using linear models.
Home-page: https://github.com/pfh/fitnoise
Author: Paul Harrison
Author-email: paul.harrison@monash.edu
License: UNKNOWN
Platform: UNKNOWN
